senabase/__init__.py
senabase/starterpack/__init__.py
senabase/starterpack/database.py
senabase/starterpack/log.py
senabase/starterpack/telegram.py
senabase_starterpack-0.1.8.dist-info/LICENSE
senabase_starterpack-0.1.8.dist-info/METADATA
senabase_starterpack-0.1.8.dist-info/WHEEL
senabase_starterpack-0.1.8.dist-info/top_level.txt
senabase_starterpack-0.1.8.dist-info/RECORD
