Metadata-Version: 2.1
Name: senabase-starterpack
Version: 0.1.8
Summary: senabase starterpack library
Home-page: https://github.com/parkssie/senabase-starterpack
Author: Jungkyu Park
Author-email: parkssie@me.com
Requires-Python: >=3.10
License-File: LICENSE
Requires-Dist: psycopg2-binary (>=2.9.1)
Requires-Dist: pyyaml (>=6.0)
Requires-Dist: requests (>=2.30.0)
